{".platform-linux atom-workspace atom-text-editor:not([mini])":{"ctrl-shift-enter":"editor:newline-above","ctrl-i":"editor:indent-selected-rows","ctrl-o":"editor:outdent-selected-rows","ctrl-shift-up":"my:move-line-up","ctrl-shift-down":"my:move-line-down","alt-n":"window:focus-next-pane","alt-shift-n":"window:focus-previous-pane","alt-a":"find-and-replace:select-all","alt-shift-enter":"maximize-panes:maximize"},".platform-linux atom-workspace atom-text-editor:not([mini]).autocomplete-active":{"up":"my:move-up","down":"my:move-down","tab":"core:move-down","shift-tab":"core:move-up","ctrl-0":"tree-view:toggle-focus","ctrl-W":"editor:select-word"},"body":{"ctrl-shift-w":"core:close"}}